pybloqs/__init__.py
pybloqs/config.py
pybloqs/email.py
pybloqs/html.py
pybloqs/util.py
pybloqs/block/__init__.py
pybloqs/block/base.py
pybloqs/block/colors.py
pybloqs/block/convenience.py
pybloqs/block/data_tables.py
pybloqs/block/image.py
pybloqs/block/layout.py
pybloqs/block/table.py
pybloqs/block/table_formatters.py
pybloqs/block/text.py
pybloqs/block/wrap.py
pybloqs/htmlconv/__init__.py
pybloqs/htmlconv/chrome_headless.py
pybloqs/htmlconv/html_converter.py
pybloqs/htmlconv/puppeteer.js
pybloqs/htmlconv/wkhtmltox.py
pybloqs/jinja/__init__.py
pybloqs/jinja/table.html
pybloqs/plot/__init__.py
pybloqs/plot/core.py
pybloqs/plot/extras.py
pybloqs/static/__init__.py
pybloqs/static/block-core.js
pybloqs/static/highcharts-pybloqs.js
pybloqs/static/jquery-dataTables-impl.js
pybloqs/static/jquery-dataTables.js
pybloqs/static/jquery.js
pybloqs/static/jsinflate.js
pybloqs/static/css/docutils.css
pybloqs/static/css/jquery-dataTables.css
pybloqs/static/css/pybloqs_default/main.css
quangdv_pybloqs-1.2.12.dist-info/LICENSE
quangdv_pybloqs-1.2.12.dist-info/METADATA
quangdv_pybloqs-1.2.12.dist-info/WHEEL
quangdv_pybloqs-1.2.12.dist-info/top_level.txt
quangdv_pybloqs-1.2.12.dist-info/RECORD
